leviathan_ui/__init__.py
leviathan_ui/debug.py
leviathan_ui/dialogs.py
leviathan_ui/fixLights.py
leviathan_ui/inmojiTrx.py
leviathan_ui/lightsOff.py
leviathan_ui/progress_bar.py
leviathan_ui/splash.py
leviathan_ui/title_bar.py
leviathan_ui/wipeWindow.py
leviathan_ui-1.0.3.dist-info/licenses/LICENSE
leviathan_ui-1.0.3.dist-info/METADATA
leviathan_ui-1.0.3.dist-info/WHEEL
leviathan_ui-1.0.3.dist-info/top_level.txt
leviathan_ui-1.0.3.dist-info/RECORD
