Metadata-Version: 2.4
Name: leviathan-ui
Version: 1.0.3
Summary: Premium UI framework for PyQt5 with Windows 11 aesthetics, blur effects, i18n support, and modern splash screens
Author-email: Jesus Quijada <jesusquijada.gh34@gmail.com>
License: MIT
Project-URL: Homepage, https://github.com/JesusQuijada34/leviathan-ui
Project-URL: Documentation, https://github.com/JesusQuijada34/leviathan-ui#readme
Project-URL: Repository, https://github.com/JesusQuijada34/leviathan-ui
Project-URL: Issues, https://github.com/JesusQuijada/leviathan-ui/issues
Keywords: pyqt5,ui,windows11,blur,splash,frameless,modern-ui,i18n
Classifier: Development Status :: 4 - Beta
Classifier: Intended Audience :: Developers
Classifier: License :: OSI Approved :: MIT License
Classifier: Programming Language :: Python :: 3
Classifier: Programming Language :: Python :: 3.8
Classifier: Programming Language :: Python :: 3.9
Classifier: Programming Language :: Python :: 3.10
Classifier: Programming Language :: Python :: 3.11
Classifier: Programming Language :: Python :: 3.12
Classifier: Operating System :: Microsoft :: Windows
Classifier: Topic :: Software Development :: User Interfaces
Classifier: Topic :: Software Development :: Libraries :: Python Modules
Requires-Python: >=3.8
License-File: LICENSE
Requires-Dist: PyQt5>=5.15.0
Requires-Dist: Pillow>=9.0.0
Dynamic: license-file
